odoo/addons/account_peppol_backport/README.rst
odoo/addons/account_peppol_backport/__init__.py
odoo/addons/account_peppol_backport/__manifest__.py
odoo/addons/account_peppol_backport/data/cron.xml
odoo/addons/account_peppol_backport/demo/account_peppol_demo.xml
odoo/addons/account_peppol_backport/i18n/account_peppol.pot
odoo/addons/account_peppol_backport/i18n/ar.po
odoo/addons/account_peppol_backport/i18n/az.po
odoo/addons/account_peppol_backport/i18n/bg.po
odoo/addons/account_peppol_backport/i18n/ca.po
odoo/addons/account_peppol_backport/i18n/cs.po
odoo/addons/account_peppol_backport/i18n/da.po
odoo/addons/account_peppol_backport/i18n/de.po
odoo/addons/account_peppol_backport/i18n/el.po
odoo/addons/account_peppol_backport/i18n/es.po
odoo/addons/account_peppol_backport/i18n/es_419.po
odoo/addons/account_peppol_backport/i18n/et.po
odoo/addons/account_peppol_backport/i18n/fa.po
odoo/addons/account_peppol_backport/i18n/fi.po
odoo/addons/account_peppol_backport/i18n/fr.po
odoo/addons/account_peppol_backport/i18n/he.po
odoo/addons/account_peppol_backport/i18n/hr.po
odoo/addons/account_peppol_backport/i18n/hu.po
odoo/addons/account_peppol_backport/i18n/hy.po
odoo/addons/account_peppol_backport/i18n/id.po
odoo/addons/account_peppol_backport/i18n/is.po
odoo/addons/account_peppol_backport/i18n/it.po
odoo/addons/account_peppol_backport/i18n/ja.po
odoo/addons/account_peppol_backport/i18n/ko.po
odoo/addons/account_peppol_backport/i18n/lt.po
odoo/addons/account_peppol_backport/i18n/lv.po
odoo/addons/account_peppol_backport/i18n/nb.po
odoo/addons/account_peppol_backport/i18n/nl.po
odoo/addons/account_peppol_backport/i18n/pl.po
odoo/addons/account_peppol_backport/i18n/pt.po
odoo/addons/account_peppol_backport/i18n/pt_BR.po
odoo/addons/account_peppol_backport/i18n/ro.po
odoo/addons/account_peppol_backport/i18n/ru.po
odoo/addons/account_peppol_backport/i18n/sk.po
odoo/addons/account_peppol_backport/i18n/sl.po
odoo/addons/account_peppol_backport/i18n/sr.po
odoo_addon_account_peppol_backport-16.0.1.0.0.11.dist-info/METADATA
odoo_addon_account_peppol_backport-16.0.1.0.0.11.dist-info/WHEEL
odoo_addon_account_peppol_backport-16.0.1.0.0.11.dist-info/top_level.txt
odoo_addon_account_peppol_backport-16.0.1.0.0.11.dist-info/RECORD
